lsmaker/__init__.py
lsmaker/_version.py
lsmaker/diagnostics.py
lsmaker/lsmaker.py
lsmaker/tests/__init__.py
lsmaker/tests/conftest.py
lsmaker/tests/t001_test.py
lsmaker/tests/t002_test.py
lsmaker/tests/t003_test.py
lsmaker/tests/test_notebooks.py
lsmaker/utils/__init__.py
lsmaker/utils/gflow_results.py
linesink_maker-0.2.0.dist-info/AUTHORS.rst
linesink_maker-0.2.0.dist-info/LICENSE.md
linesink_maker-0.2.0.dist-info/METADATA
linesink_maker-0.2.0.dist-info/WHEEL
linesink_maker-0.2.0.dist-info/top_level.txt
linesink_maker-0.2.0.dist-info/RECORD
