Metadata-Version: 2.1
Name: linesink-maker
Version: 0.2.0
Summary: Rapid creation of linesink elements for streamf network simulation in GFLOW.
Home-page: https://github.com/aleaf/linesink-maker
Author: Andrew Leaf
Author-email: aleaf@usgs.gov
License: BSD (3-clause)
Classifier: Development Status :: 2 - Pre-Alpha
Classifier: Natural Language :: English
Classifier: Programming Language :: Python :: 3
Requires-Python: >=3.7
License-File: LICENSE.md
License-File: AUTHORS.rst
